fracmechpy/__init__.py
fracmechpy/incpoly.py
fracmechpy/secant.py
fracmechpy-0.0.3.dist-info/LICENSE.txt
fracmechpy-0.0.3.dist-info/METADATA
fracmechpy-0.0.3.dist-info/WHEEL
fracmechpy-0.0.3.dist-info/top_level.txt
fracmechpy-0.0.3.dist-info/RECORD
