Metadata-Version: 2.2
Name: fracmechpy
Version: 0.0.3
Summary: A Python package for fracture growth modeling.
Author-email: Danial Haselibozchaloee <dhaselib@gmail.com>
License: MIT License
Requires-Python: >=3.7
License-File: LICENSE.txt
Requires-Dist: numpy
Requires-Dist: scipy
Provides-Extra: dev
Requires-Dist: pytest; extra == "dev"
